scim2_cli/__init__.py
scim2_cli/create.py
scim2_cli/delete.py
scim2_cli/py.typed
scim2_cli/query.py
scim2_cli/replace.py
scim2_cli/search.py
scim2_cli/test.py
scim2_cli/utils.py
scim2_cli-0.2.3.dist-info/METADATA
scim2_cli-0.2.3.dist-info/WHEEL
scim2_cli-0.2.3.dist-info/entry_points.txt
scim2_cli-0.2.3.dist-info/licenses/LICENSE.md
scim2_cli-0.2.3.dist-info/RECORD
