Metadata-Version: 2.4
Name: scim2-cli
Version: 0.2.3
Summary: SCIM application development CLI
Project-URL: documentation, https://scim2-cli.readthedocs.io
Project-URL: repository, https://github.com/python-scim/scim2-cli
Project-URL: changelog, https://scim2-cli.readthedocs.io/en/latest/changelog.html
Project-URL: funding, https://github.com/sponsors/python-scim
Author-email: Yaal Coop <contact@yaal.coop>
License:                                  Apache License
License-File: LICENSE.md
Keywords: provisioning,rfc7643,rfc7644,scim,scim2
Classifier: Development Status :: 3 - Alpha
Classifier: Environment :: Web Environment
Classifier: Intended Audience :: Developers
Classifier: License :: OSI Approved :: Apache Software License
Classifier: Operating System :: OS Independent
Classifier: Programming Language :: Python
Classifier: Programming Language :: Python :: 3.10
Classifier: Programming Language :: Python :: 3.11
Classifier: Programming Language :: Python :: 3.12
Classifier: Programming Language :: Python :: 3.13
Classifier: Programming Language :: Python :: Implementation :: CPython
Requires-Python: >=3.10
Requires-Dist: click>=8.1.7
Requires-Dist: pydanclick>=0.4.0
Requires-Dist: pygments>=2.18.0
Requires-Dist: scim2-client>=0.4.3
Requires-Dist: scim2-tester[httpx]>=0.1.10
Requires-Dist: sphinx-click-rst-to-ansi-formatter>=0.1.0
